keyval_storage/__init__.py
keyval_storage/cli.py
keyval_storage/config.py
keyval_storage/config_and_key_value_storage_data_model.py
keyval_storage/config_provider.py
keyval_storage/config_storage_interaction.py
keyval_storage/constants.py
keyval_storage/exceptions.py
keyval_storage/key_value_storage.py
keyval_storage/storage.py
keyval_storage/storage_provider.py
tests/__init__.py
tests/test_cli.py
tests/test_storage.py
atari_monk_keyval_storage-0.1.1.dist-info/LICENSE
atari_monk_keyval_storage-0.1.1.dist-info/METADATA
atari_monk_keyval_storage-0.1.1.dist-info/WHEEL
atari_monk_keyval_storage-0.1.1.dist-info/entry_points.txt
atari_monk_keyval_storage-0.1.1.dist-info/top_level.txt
atari_monk_keyval_storage-0.1.1.dist-info/RECORD
