Metadata-Version: 2.1
Name: atari-monk-keyval-storage
Version: 0.1.1
Summary: A simple JSON-based key-value storage library
Home-page: https://github.com/atari-monk/keyval-storage
Author: atari monk
Author-email: atari.monk1@gmail.com
Classifier: Programming Language :: Python :: 3
Classifier: License :: OSI Approved :: MIT License
Classifier: Operating System :: OS Independent
Requires-Python: >=3.6
License-File: LICENSE
Requires-Dist: atari-monk-pytoolbox
Requires-Dist: atari-monk-cli-logger
